<?xml version="1.0" encoding="UTF-8"?>
<con:soapui-project id="1a47d29a-b8aa-475f-b77b-2e3191a1b66e" activeEnvironment="Default" name="REST Project 3" soapui-version="5.5.0" xmlns:con="http://eviware.com/soapui/config"><con:settings/><con:interface xsi:type="con:RestService" id="c0ec438c-4c95-4b3f-abb7-2119b5584d3c" wadlVersion="http://wadl.dev.java.net/2009/02" name="http://10.10.34.184:8080" type="rest" xmlns:xsi="http://www.w3.org/2001/XMLSchema-instance"><con:settings/><con:definitionCache/><con:endpoints><con:endpoint>http://10.10.34.184:8080</con:endpoint></con:endpoints><con:resource name="Promotion" path="/boxoffice-services/services/rest/promotion/allocateCredits" id="3b8ada20-cb37-4cd4-8510-8386361c2a48"><con:settings/><con:parameters/><con:method name="Promotion 1" id="0becf85a-d960-4e4c-aa3e-f0ddcbc70e68" method="POST"><con:settings/><con:parameters/><con:representation type="RESPONSE"><con:mediaType>application/json</con:mediaType><con:status>200 201</con:status><con:params/><con:element xmlns:ping="http://10.10.34.184/boxoffice-services/services/rest/promotion/ping">ping:Response</con:element></con:representation><con:representation type="FAULT"><con:mediaType xsi:nil="true"/><con:status>405</con:status><con:params/><con:element>data</con:element></con:representation><con:representation type="REQUEST"><con:mediaType>application/json</con:mediaType><con:params/></con:representation><con:representation type="FAULT"><con:mediaType xsi:nil="true"/><con:status>405</con:status><con:params/><con:element>data</con:element></con:representation><con:request name="Request 1" id="3235edd5-a801-4094-a5d0-e6aa5babf688" mediaType="application/json" postQueryString="false"><con:settings><con:setting id="com.eviware.soapui.impl.wsdl.WsdlRequest@request-headers">&lt;xml-fragment/></con:setting></con:settings><con:endpoint>http://10.10.34.184:8080</con:endpoint><con:request>{
   "promotionName":"Discovery",
   "saIdentityNumber":"5107165145085"	
 
}</con:request><con:originalUri>http://10.10.34.184/boxoffice-services/services/rest/promotion/ping</con:originalUri><con:credentials><con:authType>No Authorization</con:authType></con:credentials><con:jmsConfig JMSDeliveryMode="PERSISTENT"/><con:jmsPropertyConfig/><con:parameters/><con:parameterOrder/></con:request></con:method></con:resource></con:interface><con:properties/><con:wssContainer/><con:oAuth2ProfileContainer/><con:oAuth1ProfileContainer/></con:soapui-project>